nonebot_plugin_aichat/__init__.py
nonebot_plugin_aichat/config.py
nonebot_plugin_aichat/data/characters.json
nonebot_plugin_aichat/data/config.json
nonebot_plugin_aichat/data/groups.json
nonebot_plugin_aichat/data/memory.json
nonebot_plugin_aichat/memory_manager.py
nonebot_plugin_aichat/static/index.html
nonebot_plugin_aichat/web_admin.py
nonebot_plugin_aichatbyluxis-0.1.4.dist-info/licenses/LICENSE
nonebot_plugin_aichatbyluxis-0.1.4.dist-info/METADATA
nonebot_plugin_aichatbyluxis-0.1.4.dist-info/WHEEL
nonebot_plugin_aichatbyluxis-0.1.4.dist-info/RECORD
