Metadata-Version: 2.4
Name: nonebot-plugin-aichatbyluxis
Version: 0.1.4
Summary: 一个支持 DeepSeek API 的角色扮演插件。
License: MIT
License-File: LICENSE
Author: 47Lux
Author-email: 2777433165@qq.com
Requires-Python: >=3.8,<4.0
Classifier: License :: OSI Approved :: MIT License
Classifier: Programming Language :: Python :: 3
Classifier: Programming Language :: Python :: 3.8
Classifier: Programming Language :: Python :: 3.9
Classifier: Programming Language :: Python :: 3.10
Classifier: Programming Language :: Python :: 3.11
Classifier: Programming Language :: Python :: 3.12
Classifier: Programming Language :: Python :: 3.13
Classifier: Programming Language :: Python :: 3.14
Requires-Dist: fastapi (>=0.93.0)
Requires-Dist: httpx (>=0.23.0)
Requires-Dist: nonebot-adapter-onebot (>=2.4.0,<3.0.0)
Requires-Dist: nonebot2 (>=2.2.0,<3.0.0)
Requires-Dist: pydantic (>=1.10.0,<3.0.0)
Project-URL: Homepage, https://github.com/47Lux/nonebot-plugin-aichat
Project-URL: Repository, https://github.com/47Lux/nonebot-plugin-aichat
